geomagdata/__init__.py
geomagdata/base.py
geomagdata/io.py
geomagdata/utils.py
geomagdata/web.py
geomagdata/data/May2016Rpt.txt
geomagdata-1.6.1.dist-info/LICENSE.txt
geomagdata-1.6.1.dist-info/METADATA
geomagdata-1.6.1.dist-info/WHEEL
geomagdata-1.6.1.dist-info/top_level.txt
geomagdata-1.6.1.dist-info/RECORD
